<?xml version="1.0" encoding="UTF-8" standalone="yes"?>
<p:sld xmlns:a="http://schemas.openxmlformats.org/drawingml/2006/main" xmlns:r="http://schemas.openxmlformats.org/officeDocument/2006/relationships" xmlns:p="http://schemas.openxmlformats.org/presentationml/2006/main"><p:cSld><p:spTree><p:nvGrpSpPr><p:cNvPr id="1" name=""/><p:cNvGrpSpPr/><p:nvPr/></p:nvGrpSpPr><p:grpSpPr><a:xfrm><a:off x="0" y="0"/><a:ext cx="0" cy="0"/><a:chOff x="0" y="0"/><a:chExt cx="0" cy="0"/></a:xfrm></p:grpSpPr><p:sp><p:nvSpPr><p:cNvPr id="38913" name="Title 1"/><p:cNvSpPr><a:spLocks noGrp="1"/></p:cNvSpPr><p:nvPr><p:ph type="title"/></p:nvPr></p:nvSpPr><p:spPr/><p:txBody><a:bodyPr/><a:lstStyle/><a:p><a:r><a:rPr lang="en-US" dirty="0" smtClean="0"/><a:t>The Ashville Project </a:t></a:r></a:p></p:txBody></p:sp><p:sp><p:nvSpPr><p:cNvPr id="3" name="Content Placeholder 2"/><p:cNvSpPr><a:spLocks noGrp="1"/></p:cNvSpPr><p:nvPr><p:ph idx="1"/></p:nvPr></p:nvSpPr><p:spPr/><p:txBody><a:bodyPr rtlCol="0"><a:normAutofit/></a:bodyPr><a:lstStyle/><a:p><a:pPr fontAlgn="auto"><a:spcAft><a:spcPts val="0"/></a:spcAft><a:buFont typeface="Arial" pitchFamily="34" charset="0"/><a:buChar char="•"/><a:defRPr/></a:pPr><a:r><a:rPr lang="en-US" b="1" dirty="0" smtClean="0"/><a:t>What is the Return on Investment (ROI) seen by the City?</a:t></a:r><a:br><a:rPr lang="en-US" b="1" dirty="0" smtClean="0"/></a:br><a:r><a:rPr lang="en-US" dirty="0" smtClean="0"/><a:t>Results of published data indicate that the City saves about $4.00 for every $1.00 they invest in the program.  These results have been fairly consistent across the board for other businesses who have appropriately implemented the model</a:t></a:r></a:p><a:p><a:pPr fontAlgn="auto"><a:spcAft><a:spcPts val="0"/></a:spcAft><a:buFont typeface="Arial" pitchFamily="34" charset="0"/><a:buChar char="•"/><a:defRPr/></a:pPr><a:endParaRPr lang="en-US" dirty="0"/></a:p></p:txBody></p:sp><p:sp><p:nvSpPr><p:cNvPr id="4" name="Footer Placeholder 3"/><p:cNvSpPr><a:spLocks noGrp="1"/></p:cNvSpPr><p:nvPr><p:ph type="ftr" sz="quarter" idx="11"/></p:nvPr></p:nvSpPr><p:spPr/><p:txBody><a:bodyPr/><a:lstStyle/><a:p><a:pPr><a:defRPr/></a:pPr><a:r><a:rPr lang="en-US" dirty="0"/><a:t>http://www.theashvilleproject.net</a:t></a:r></a:p></p:txBody></p:sp></p:spTree><p:custDataLst><p:tags r:id="rId1"/></p:custDataLst><p:extLst><p:ext uri="{BB962C8B-B14F-4D97-AF65-F5344CB8AC3E}"><p14:creationId xmlns:p14="http://schemas.microsoft.com/office/powerpoint/2010/main" xmlns="" val="3233241861"/></p:ext></p:extLst></p:cSld><p:clrMapOvr><a:masterClrMapping/></p:clrMapOvr><p:timing><p:tnLst><p:par><p:cTn id="1" dur="indefinite" restart="never" nodeType="tmRoot"/></p:par></p:tnLst></p:timing></p:sld>